dotmotif/__init__.py
dotmotif/utils.py
dotmotif/executors/Executor.py
dotmotif/executors/GrandIsoExecutor.py
dotmotif/executors/Neo4jExecutor.py
dotmotif/executors/NetworkXExecutor.py
dotmotif/executors/NeuPrintExecutor.py
dotmotif/executors/__init__.py
dotmotif/executors/test_dm_cypher.py
dotmotif/executors/test_grandisoexecutor.py
dotmotif/executors/test_neo4jexecutor.py
dotmotif/executors/test_networkxexecutor.py
dotmotif/executors/test_neuprintexecutor.py
dotmotif/ingest/__init__.py
dotmotif/ingest/test_ingest.py
dotmotif/parsers/__init__.py
dotmotif/parsers/v2/__init__.py
dotmotif/parsers/v2/grammar.lark
dotmotif/parsers/v2/test_v2_parser.py
dotmotif/tests/__init__.py
dotmotif/tests/test_dm_flags.py
dotmotif/tests/test_multigraphs.py
dotmotif/tests/test_utils.py
dotmotif/validators/__init__.py
dotmotif/validators/test_dm_illegal_operators.py
dotmotif-0.17.0.dist-info/METADATA
dotmotif-0.17.0.dist-info/WHEEL
dotmotif-0.17.0.dist-info/licenses/LICENSE
dotmotif-0.17.0.dist-info/RECORD
