Metadata-Version: 2.4
Name: dotmotif
Version: 0.17.0
Summary: Find graph motifs using simple, intuitive notation.
Author-email: Jordan Matelsky <jordan.matelsky@jhuapl.edu>
License-File: LICENSE
Requires-Python: >=3.9
Requires-Dist: grandiso>=2.1.1
Requires-Dist: lark>=1.3.1
Requires-Dist: networkx>=3.1
Requires-Dist: neuprint-python>=0.4.25
Requires-Dist: numpy>=1.24.3
Requires-Dist: pandas>=2.0.1
Requires-Dist: py2neo>=2021.2.4
